README.rst
setup.py
pycccl/__init__.py
pycccl/base.py
pycccl/settings.py
pycccl.egg-info/PKG-INFO
pycccl.egg-info/SOURCES.txt
pycccl.egg-info/dependency_links.txt
pycccl.egg-info/not-zip-safe
pycccl.egg-info/top_level.txt
pycccl/exchanges/__init__.py
pycccl/exchanges/binance.py
pycccl/exchanges/bitbay.py
pycccl/exchanges/bitfinex.py
pycccl/exchanges/bitstamp.py
pycccl/exchanges/blinktrade.py
pycccl/exchanges/cexio.py
pycccl/exchanges/liqui.py
pycccl/exchanges/poloniex.py
pycccl/exchanges/yobit.py