Metadata-Version: 1.0
Name: pycccl
Version: 0.1.1
Summary: Python (C)rypto (C)urrency (C)ommon (L)ibrary.
Home-page: http://github.com/beraldoleal/pycccl
Author: Beraldo Leal
Author-email: beraldo@gmail.com
License: MIT
Platform: UNKNOWN
